sopel_slap/__init__.py
sopel_slap/config.py
sopel_slap/plugin.py
sopel_slap/util.py
sopel_slap-0.4.2.dist-info/licenses/COPYING
sopel_slap-0.4.2.dist-info/METADATA
sopel_slap-0.4.2.dist-info/WHEEL
sopel_slap-0.4.2.dist-info/entry_points.txt
sopel_slap-0.4.2.dist-info/top_level.txt
sopel_slap-0.4.2.dist-info/RECORD
