Metadata-Version: 2.4
Name: sopel-slap
Version: 0.4.2
Summary: Plugin for Sopel that lets users slap each other in fun ways
Author: dgw, Michael Yanovich
Maintainer: dgw
License-Expression: EFL-2.0
Project-URL: Homepage, https://github.com/sopel-irc/sopel-slap
Project-URL: Bug Tracker, https://github.com/sopel-irc/sopel-slap/issues
Keywords: sopel,plugin,slap,pranks,bot,irc
Platform: Linux x86, x86-64
Classifier: Development Status :: 5 - Production/Stable
Classifier: Intended Audience :: Developers
Classifier: Intended Audience :: System Administrators
Classifier: Operating System :: POSIX :: Linux
Classifier: Programming Language :: Python :: 3 :: Only
Classifier: Programming Language :: Python :: 3.8
Classifier: Programming Language :: Python :: 3.9
Classifier: Programming Language :: Python :: 3.10
Classifier: Programming Language :: Python :: 3.11
Classifier: Programming Language :: Python :: 3.12
Classifier: Topic :: Communications :: Chat :: Internet Relay Chat
Requires-Python: <4,>=3.8
License-File: COPYING
Requires-Dist: sopel>=7.1
Dynamic: license-file
